MANIFEST.in
README.rst
setup.py
angus_web_visu.egg-info/PKG-INFO
angus_web_visu.egg-info/SOURCES.txt
angus_web_visu.egg-info/dependency_links.txt
angus_web_visu.egg-info/requires.txt
angus_web_visu.egg-info/top_level.txt
angusvisu/__init__.py
angusvisu/webinterface/__init__.py
angusvisu/webinterface/index.html
angusvisu/webinterface/mjpegserver.py
angusvisu/webinterface/notifier.py
angusvisu/webinterface/server.py
angusvisu/webinterface/worker.py