Metadata-Version: 1.0
Name: angus-web-visu
Version: 1.0.5
Summary: Angus Visualization Toolkit
Home-page: http://www.angus.ai/
Author: Aurélien Moreau
Author-email: aurelien.moreau@angus.ai
License: Apache v2.0
Platform: UNKNOWN
